README.txt
setup.py
cropresize/__init__.py
cropresize.egg-info/PKG-INFO
cropresize.egg-info/SOURCES.txt
cropresize.egg-info/dependency_links.txt
cropresize.egg-info/entry_points.txt
cropresize.egg-info/not-zip-safe
cropresize.egg-info/top_level.txt