Metadata-Version: 1.0
Name: cropresize
Version: 0.1.6
Summary: crop and resize an image without doing the math yourself
Home-page: http://pypi.python.org/pypi/cropresize
Author: Jeff Hammel
Author-email: k0scist@gmail.com
License: GPL
Keywords: image
Platform: UNKNOWN
